MANIFEST.in
setup.py
lerrylib/__init__.py
lerrylib/cache.py
lerrylib/db_tools.py
lerrylib/extract.py
lerrylib/highlight.py
lerrylib/jsdict.py
lerrylib/jsonrpc.py
lerrylib/lerry_signal.py
lerrylib/pg_pool.py
lerrylib/string_tools.py
lerrylib/time_tools.py
lerrylib.egg-info/PKG-INFO
lerrylib.egg-info/SOURCES.txt
lerrylib.egg-info/dependency_links.txt
lerrylib.egg-info/not-zip-safe
lerrylib.egg-info/requires.txt
lerrylib.egg-info/top_level.txt
lerrylib/Bot/__init__.py
lerrylib/Bot/_bot.py
lerrylib/Bot/bot.py
lerrylib/Bot/route.py