Metadata-Version: 1.0
Name: lerrylib
Version: 0.3.11
Summary: Some common use functions
Home-page: https://bitbucket.org/lerry/lerrylib
Author: Lerry
Author-email: lvdachao@gmail.com
License: UNKNOWN
Platform: UNKNOWN
